recipe_tool/__init__.py
recipe_tool/app.py
recipe_tool-0.1.3.dist-info/METADATA
recipe_tool-0.1.3.dist-info/WHEEL
recipe_tool-0.1.3.dist-info/entry_points.txt
recipe_tool-0.1.3.dist-info/RECORD
