Metadata-Version: 2.4
Name: recipe-tool
Version: 0.1.3
Summary: A tool for executing natural language recipe-like instructions
Author: MADE:Explorations Team
License-Expression: MIT
Requires-Python: >=3.11
Requires-Dist: recipe-executor
